pydicom_tools/__init__.py
pydicom_tools/bev.py
pydicom_tools/ct.py
pydicom_tools/dose.py
pydicom_tools/drr.py
pydicom_tools/structure.py
pydicom_tools/tests/__init__.py
pydicom_tools/tests/test_ct.py
pydicom_tools/tests/test_structure.py
pydicom_tools-0.0.10.dist-info/LICENSE
pydicom_tools-0.0.10.dist-info/METADATA
pydicom_tools-0.0.10.dist-info/WHEEL
pydicom_tools-0.0.10.dist-info/top_level.txt
pydicom_tools-0.0.10.dist-info/RECORD
