Metadata-Version: 2.1
Name: pydicom-tools
Version: 0.0.10
Summary: Tools for dicom RT analysis with pydicom
Home-page: https://github.com/wkt84/pydicom-tools
Author: Akihisa Wakita
Author-email: wakita84@gmail.com
License: UNKNOWN
Platform: UNKNOWN
Classifier: Programming Language :: Python :: 3
Classifier: License :: OSI Approved :: MIT License
Classifier: Operating System :: OS Independent
License-File: LICENSE
Requires-Dist: pydicom
Requires-Dist: numpy
Requires-Dist: matplotlib
